pybel_ols/__init__.py
pybel_ols/__main__.py
pybel_ols/cli.py
pybel_ols/ols_utils.py
pybel_ols-0.0.1.dist-info/LICENSE
pybel_ols-0.0.1.dist-info/METADATA
pybel_ols-0.0.1.dist-info/WHEEL
pybel_ols-0.0.1.dist-info/entry_points.txt
pybel_ols-0.0.1.dist-info/top_level.txt
pybel_ols-0.0.1.dist-info/zip-safe
pybel_ols-0.0.1.dist-info/RECORD
