Metadata-Version: 2.1
Name: pybel-ols
Version: 0.0.1
Summary: A package for building BEL resource files with the EBI Ontology Lookup Service.
Home-page: https://github.com/pybel/pybel-ols
Author: Charles Tapley Hoyt
Author-email: charles.hoyt@scai.fraunhofer.de
Maintainer: Charles Tapley Hoyt
Maintainer-email: charles.hoyt@scai.fraunhofer.de
License: MIT License
Download-URL: https://github.com/pybel/pybel-ols/releases
Project-URL: Bug Tracker, https://github.com/pybel/pybel-ols/issues
Project-URL: Source Code, https://github.com/pybel/pybel-ols
Keywords: Biological Expression Language,BEL,Semantic Web,Networks Biology,Systems Biology,Ontologies
Platform: UNKNOWN
Classifier: Development Status :: 1 - Planning
Classifier: Intended Audience :: Developers
Classifier: License :: OSI Approved :: MIT License
Classifier: Operating System :: OS Independent
Classifier: Programming Language :: Python
Classifier: Programming Language :: Python :: 3.6
Classifier: Programming Language :: Python :: 3.7
Classifier: Programming Language :: Python :: 3 :: Only
Requires-Python: >=3.6
Requires-Dist: pybel
Requires-Dist: bel-resources (>=0.0.2)
Requires-Dist: click
Requires-Dist: ols-client
Provides-Extra: docs
Requires-Dist: sphinx ; extra == 'docs'
Requires-Dist: sphinx-rtd-theme ; extra == 'docs'
Requires-Dist: sphinx-click ; extra == 'docs'
Requires-Dist: sphinx-autodoc-typehints ; extra == 'docs'
